pyearthdata/__init__.py
pyearthdata/_version.py
pyearthdata/airs.py
pyearthdata/power.py
pyearthdata/utils.py
PyEarthData-1.1.0.dist-info/LICENSE
PyEarthData-1.1.0.dist-info/METADATA
PyEarthData-1.1.0.dist-info/WHEEL
PyEarthData-1.1.0.dist-info/top_level.txt
PyEarthData-1.1.0.dist-info/RECORD
