Metadata-Version: 2.1
Name: PyEarthData
Version: 1.1.0
Summary: Python Package for grabbing earth surface and atmosphere data
Home-page: https://github.com/ayushanand18/PyEarthData
Author: Ayush Anand
License: MIT
Project-URL: Documentation, https://ayushanand18.github.io/PyEarthData/
Project-URL: Bug Tracker, https://github.com/ayushanand18/PyEarthData/issues
Project-URL: Source Code, https://github.com/ayushanand18/PyEarthData
Classifier: Development Status :: 5 - Production/Stable
Classifier: Intended Audience :: Science/Research
Classifier: License :: OSI Approved :: MIT License
Classifier: Operating System :: OS Independent
Classifier: Natural Language :: English
Classifier: Programming Language :: Python :: 3
Classifier: Topic :: Scientific/Engineering :: Atmospheric Science
Requires-Python: >=3.7
License-File: LICENSE
Requires-Dist: requests (>2.7)
